embrpc/__about__.py
embrpc/__init__.py
embrpc/main.py
embrpc/rpc.py
embrpc/rpcscp.py
embrpc-0.0.3.dist-info/METADATA
embrpc-0.0.3.dist-info/WHEEL
embrpc-0.0.3.dist-info/entry_points.txt
embrpc-0.0.3.dist-info/licenses/LICENSE
embrpc-0.0.3.dist-info/RECORD
